colonpython/__init__.py
colonpython-0.0.3.dist-info/LICENSE
colonpython-0.0.3.dist-info/METADATA
colonpython-0.0.3.dist-info/WHEEL
colonpython-0.0.3.dist-info/top_level.txt
colonpython-0.0.3.dist-info/RECORD
