Metadata-Version: 2.1
Name: colonpython
Version: 0.0.3
Summary: A programming language that transpiles to python and centres around colons (hence the name).
Author: RadioactiveRocket
Classifier: Programming Language :: Python :: 3
Classifier: License :: OSI Approved :: MIT License
Classifier: Operating System :: OS Independent
Requires-Python: >=3.7
License-File: LICENSE
